simple_arcgis_wrapper/__init__.py
simple_arcgis_wrapper/arcgis_api.py
simple_arcgis_wrapper/base_api.py
simple_arcgis_wrapper/exceptions.py
simple_arcgis_wrapper/field_types.py
simple_arcgis_wrapper/fields.py
simple_arcgis_wrapper/models.py
simple_arcgis_wrapper/services_api.py
simple_arcgis_wrapper/users_api.py
simple_arcgis_wrapper-1.0.5.dist-info/LICENSE
simple_arcgis_wrapper-1.0.5.dist-info/METADATA
simple_arcgis_wrapper-1.0.5.dist-info/WHEEL
simple_arcgis_wrapper-1.0.5.dist-info/top_level.txt
simple_arcgis_wrapper-1.0.5.dist-info/RECORD
