Metadata-Version: 2.1
Name: simple-arcgis-wrapper
Version: 1.0.5
Summary: A simple wrapper for interacting with the ArcGIS Online REST API.
Home-page: https://github.com/caracal-cloud/simple-arcgis-wrapper
Author: Casey Slaught
Author-email: casey@caracal.cloud
License: MIT
Keywords: arcgis gis rest api wrapper
Platform: UNKNOWN
Classifier: Development Status :: 3 - Alpha
Classifier: Intended Audience :: Developers
Classifier: Programming Language :: Python :: 3
Classifier: License :: OSI Approved :: MIT License
Classifier: Operating System :: OS Independent
Requires-Python: >=3.5
Requires-Dist: requests (>=2.10.0)
